setup.cfg
setup.py
django_queryset_iterator.egg-info/PKG-INFO
django_queryset_iterator.egg-info/SOURCES.txt
django_queryset_iterator.egg-info/dependency_links.txt
django_queryset_iterator.egg-info/top_level.txt
queryset_iterator/__init__.py
queryset_iterator/core.py