Metadata-Version: 1.0
Name: django-queryset-iterator
Version: 0.1.1
Summary: Iterate over large Data-sets in Django efficiently.
Home-page: https://github.com/Andrew-Crosio/django-queryset-iterator
Author: Andrew Crosio
Author-email: andrew@andrewcrosio.com
License: UNKNOWN
Platform: UNKNOWN
